Metadata-Version: 2.1
Name: pyfmm_gui
Version: 0.2.2
Summary: A simple GUI of PyFMM
Home-page: https://github.com/Dengda98/PyFMM-GUI
Author: Zhu Dengda
Author-email: zhudengda@mail.iggcas.ac.cn
Requires-Python: >=3.9
License-File: LICENSE
